test_gpu.py
hf-test/tpu_benchmark.py
hfperf/tpu_benchmark.py
hftest/tpu_benchmark.py
packages/test_gpu.py
hfperf-0.0.0.dist-info/METADATA
hfperf-0.0.0.dist-info/WHEEL
hfperf-0.0.0.dist-info/top_level.txt
hfperf-0.0.0.dist-info/RECORD
